app/main.py
app/api/router.py
app/api/endpoints/bilibili_web.py
app/api/endpoints/douyin_web.py
app/api/endpoints/download.py
app/api/endpoints/hybrid_parsing.py
app/api/endpoints/ios_shortcut.py
app/api/endpoints/tiktok_app.py
app/api/endpoints/tiktok_web.py
app/api/models/APIResponseModel.py
app/web/app.py
app/web/views/About.py
app/web/views/Document.py
app/web/views/Downloader.py
app/web/views/EasterEgg.py
app/web/views/ParseVideo.py
app/web/views/Shortcuts.py
app/web/views/ViewsUtils.py
crawlers/base_crawler.py
crawlers/bilibili/web/config.yaml
crawlers/bilibili/web/endpoints.py
crawlers/bilibili/web/models.py
crawlers/bilibili/web/utils.py
crawlers/bilibili/web/web_crawler.py
crawlers/bilibili/web/wrid.py
crawlers/douyin/web/abogus.py
crawlers/douyin/web/config.yaml
crawlers/douyin/web/endpoints.py
crawlers/douyin/web/models.py
crawlers/douyin/web/utils.py
crawlers/douyin/web/web_crawler.py
crawlers/douyin/web/xbogus.py
crawlers/hybrid/hybrid_crawler.py
crawlers/tiktok/app/app_crawler.py
crawlers/tiktok/app/config.yaml
crawlers/tiktok/app/endpoints.py
crawlers/tiktok/app/models.py
crawlers/tiktok/web/config.yaml
crawlers/tiktok/web/endpoints.py
crawlers/tiktok/web/models.py
crawlers/tiktok/web/utils.py
crawlers/tiktok/web/web_crawler.py
crawlers/utils/api_exceptions.py
crawlers/utils/deprecated.py
crawlers/utils/logger.py
crawlers/utils/utils.py
douyin_tiktok_scraper250605-0.0.4.dist-info/licenses/LICENSE
douyin_tiktok_scraper250605-0.0.4.dist-info/METADATA
douyin_tiktok_scraper250605-0.0.4.dist-info/WHEEL
douyin_tiktok_scraper250605-0.0.4.dist-info/top_level.txt
douyin_tiktok_scraper250605-0.0.4.dist-info/RECORD
